Workbook
Name Acq_End: [1]Inputs!$E$12
Name Acq_Start: [1]Inputs!$E$10
Name Days_Yr: [1]Names!$F$11
Name Million: [1]Names!$F$17
Name Model_Start: [1]Inputs!$E$7
Name Months_Qtr: [1]Names!$F$14
Name Months_Yr: [1]Names!$F$12
Name Name_Model: [1]Names!$F$8
Name Ops_End: [1]Inputs!$E$17
Name Ops_Start: [1]Inputs!$E$15
Name Qtrs_Yr: [1]Names!$F$13

Sheet Cover Page
B2: Section Number: | G2: Name of Company: | I2: BinDawood Holdings
B3: Group Number: | G3: Company Ticker: | I3: 4161 - SA
B4: Instructor Name: | G4: Market Price Date | I4: 46106 | J4: (Date)
G5: Market Price per Share | I5: 6.39
B6: Write Names of Group Members below: | G6: Intrinsic Share Price | I6: =Valuation!E35
A7: 1. | F7: (Group Leader) | G7: Up/Downside SAR
G8: Up/Downside % | J8: (Percentage)
A9: 2. | G9: Recommendation | J9: (Buy or Sell)
A11: 3.
A13: 4.
A15: 5.

Sheet Financials
A1: ='Cover Page'!I2
A2: ='Cover Page'!I3 | B2: 2022 | C2: 2023 | D2: 2024 | E2: 2025 | F2: 2025 | G2: 2026 | H2: 2027
B3: Actual | C3: Actual | D3: Actual | E3: Actual | F3: Forecast | G3: Forecast | H3: Forecast
A4: Key Assumptions
A5: Sales Growth Rate | C5: =(C34-B34)/B34 | D5: =(D34-C34)/C34 | E5: =(E34-D34)/D34 | F5: 0.06 | G5: 0.05 | H5: 0.05
A6: Tax Rate | B6: 0.2 | C6: 0.22 | D6: 0.22 | E6: 0.22 | F6: 0.22 | G6: 0.4 | H6: 0.4
A7: Interest Rate on Short-Term Debt | B7: 0.065 | C7: 0.067 | D7: 0.069 | E7: 0.071 | F7: 0.07 | G7: 0.069 | H7: 0.068
A8: Interest Rate on Long-Term Debt | B8: 0.077 | C8: 0.079 | D8: 0.081 | E8: 0.083 | F8: 0.082 | G8: 0.081 | H8: 0.08
A9: Dividend Payout Rate | B9: =(B51/B46) | C9: =(C51/C46) | D9: =(D51/D46) | E9: =(E51/E46) | F9: 0.35 | G9: 0.35 | H9: 0.35
A10: Price / Earnings | B10: =(B105/B48) | C10: =(C105/C48) | D10: =(D105/D48) | E10: =(E105/E48) | F10: 29.4 | G10: 29.4 | H10: 29.4
A11: EBITDA Growth Rate | B11: 0.1583 | C11: 0.1047 | D11: 0.085 | E11: 0.0805 | F11: 0.1071 | G11: 0.1071 | H11: 0.1071
A12: EBIT Growth Rate | B12: 82.113 | C12: 115.756 | D12: 62.225 | E12: 265.844 | F12: 0.32599462
A13: NWC Avg | E13: -0.16228134 | F13: -0.16228134
A14: Dep/Amo Avg Growth | E14: 0.024614234 | F14: 0.024614234
A15: Capex Avg | E15: 0.016846793 | F15: 0.016846793
A16: WACC | E16: 0.1 | F16: 0.1
F19: 0.8 | G19: 0.8 | H19: 0.8
F20: 14 | G20: 14 | H20: 14
E26: 0.1 | F26: 0.1
A33: Income Statement (Mil.$)
A34: Sales | B34: 73.84 | C34: 93.28 | D34: 115.93 | E34: 138.84 | F34: =(E34)*(1+F5) | G34: =(F34)*(1+G5) | H34: =(G34)*(1+H5)
A35: Cost of Goods Sold | B35: 41.83 | C35: 58.39 | D35: 75.49 | E35: 89.83 | F35: =(F34*$I$124) | G35: =(G34*$I$124) | H35: =(H34*$I$124)
A36: Gross Margin | B36: =(B34-B35) | C36: =(C34-C35) | D36: =(D34-D35) | E36: =(E34-E35) | F36: =(F34-F35) | G36: =(G34-G35) | H36: =(H34-H35)
A38: Selling, Gen & Adm Expenses | B38: 6.58 | C38: 7.28 | D38: 8.56 | E38: 10.21 | F38: =(F34*$I$127) | G38: =(G34*$I$127) | H38: =(H34*$I$127)
A39: EBITDA | B39: 678.456 | C39: 583.56 | D39: 967.578 | E39: 1133.303
B40: 398.336 | C40: 364.435 | D40: 497.756 | E40: 663.213
A41: Depreciation | B41: 5.91 | C41: 6.37 | D41: 7.31 | E41: 9.86 | F41: =(F34*$I$128) | G41: =(G34*$I$128) | H41: =(H34*$I$128)
A42: EBIT | B42: =(B36-B38-B41) | C42: =(C36-C38-C41) | D42: =(D36-D38-D41) | E42: =(E36-E38-E41) | F42: =(F36-F38-F41) | G42: =(G36-G38-G41) | H42: =(H36-H38-H41)
B43: 46.593 | C43: 39.142 | D43: 88.805 | E43: 70.329
A44: Interest Expense | B44: 4.76 | C44: 5.23 | D44: 6.69 | E44: 8.88 | F44: =(F7*E91)+(E94*F8) | G44: =(G7*F91)+(F94*G8) | H44: =(H7*G91)+(G94*H8)
A45: Taxes | B45: 6.21 | C45: 6.96 | D45: 7.52 | E45: 7.6 | F45: =(F42-F44)*F6 | G45: =(G42-G44)*G6 | H45: =(H42-H44)*H6
A46: Net Income | B46: 72.369 | C46: 59.816 | D46: 88.724 | E46: 132.8 | F46: =(F42-F44-F45) | G46: =(G42-G44-G45) | H46: =(H42-H44-H45)
A47: Shares Outstanding (Millions) | B47: 39.6 | C47: 40.36 | D47: 44.93 | E47: 53.91 | F47: =(E47)+((F98-E98)/E105) | G47: =(F47)+((G98-F98)/F105) | H47: =(G47)+((H98-G98)/G105)
A48: Earnings Per Share | B48: =(B46/B47) | C48: =(C46/C47) | D48: =(D46/D47) | E48: =(E46/E47) | F48: =(F46/F47) | G48: =(G46/G47) | H48: =(H46/H47)
B49: 1.03 | C49: 0.959 | D49: 4.032 | E49: 4.441
A50: Allocation of Net Income: | B50: 24.541 | C50: 16.605 | D50: 27.981 | E50: 22.762
A51: Dividends | B51: 130.513 | C51: 141.971 | D51: 301.349 | E51: 259.933 | F51: =(F46*F9) | G51: =(G46*G9) | H51: =(H46*H9)
A52: Change in Equity | B52: 90 | C52: 90 | D52: 101.07 | E52: 109.659 | F52: =(F46-F51) | G52: =(G46-G51) | H52: =(H46-H51)
B56: 204.798 | C56: 230.513 | D56: 276.385 | E56: 349.828
B66: 51.884 | C66: 39.989 | D66: 106.802 | E66: 104.75
B67: 51.6 | C67: 67.864 | D67: 140.601 | E67: 169.629
B68: 345.766 | C68: 379.246 | D68: 759.7 | E68: 765.689
A70: Balance Sheet (Mil.$)
A71: Assets | B71: 547.842 | C71: 695.117 | D71: 1247.166 | E71: 1458.246
A72: Current Assets | B72: 0 | C72: 0 | D72: 0 | E72: 0
A73: Cash & Equivalents | B73: 4.27 | C73: 6.38 | D73: 7.62 | E73: 8.83 | F73: =(F34*$I$144) | G73: =(G34*$I$144) | H73: =(H34*$I$144)
A74: Receivables | B74: 20.58 | C74: 24.39 | D74: 28.77 | E74: 34.11 | F74: =(F34*$I$145) | G74: =(G34*$I$145) | H74: =(H34*$I$145)
A75: Inventories | B75: 26.73 | C75: 30.45 | D75: 36.75 | E75: 43.27 | F75: =(F34*$I$146) | G75: =(G34*$I$146) | H75: =(H34*$I$146)
A76: Total Current Assets | B76: =SUM(B73:B75) | C76: =SUM(C73:C75) | D76: =SUM(D73:D75) | E76: =SUM(E73:E75) | F76: =SUM(F73:F75) | G76: =SUM(G73:G75) | H76: =SUM(H73:H75)
A78: Property, Plant & Equip. (PPE) | B78: 331.64 | C78: 423.92 | D78: 503.87 | E78: 613.28 | F78: =(F79+F80) | G78: =(G79+G80) | H78: =(H79+H80)
A79: Accumulated Depreciation | B79: 118.77 | C79: 89.118 | D79: 190.946 | E79: 186.973 | F79: =(E79+F41) | G79: =(F79+G41) | H79: =(G79+H41)
A80: Net PPE | B80: 0 | C80: 0 | D80: 0 | E80: 100.62 | F80: =(F34*$I$151) | G80: =(G34*$I$151) | H80: =(H34*$I$151)
A82: Total Assets | B82: =(B76+B80) | C82: =(C76+C80) | D82: =(D76+D80) | E82: =(E76+E80) | F82: =(F76+F80) | G82: =(G76+G80) | H82: =(H76+H80)
B83: 0 | C83: 0 | D83: 0 | E83: 0
B87: 1170 | C87: 1170 | D87: 2372.702 | E87: 2372.702
A88: Liabilities and Shareholders' Equity | B88: 498.555 | C88: 411.026 | D88: 438.804 | E88: 333.644
A89: Current Liabilities
A90: Accounts Payable | B90: 31.83 | C90: 63.43 | D90: 83.84 | E90: 94.41 | F90: =($F$34*I157) | G90: =(G34*$I$157) | H90: =(H34*$I$157)
A91: Short-term Debt | B91: 30.86 | C91: 43.03 | D91: 64.85 | E91: 79.49 | F91: =(F34*$I$158) | G91: =(G34*$I$158) | H91: =(H34*$I$158)
A92: Total Current Liabilities | B92: =SUM(B90:B91) | C92: =SUM(C90:C91) | D92: =SUM(D90:D91) | E92: =SUM(E90:E91) | F92: =SUM(F90:F91) | G92: =SUM(G90:G91) | H92: =SUM(H90:H91)
A94: Long-term Debt | B94: 58 | C94: 67 | D94: 60 | E94: 51 | F94: 83.32 | G94: 92.48 | H94: 107.71
A95: Total Liabilities | B95: =(B102-B100) | C95: =(C102-C100) | D95: =(D102-D100) | E95: =(E102-E100) | F95: =(F102-F100) | G95: =(G102-G100) | H95: =(H102-H100)
A97: Shareholders' Equity
A98: Paid-in Capital | B98: 90 | C98: 130 | D98: 160 | E98: 220 | F98: 260 | G98: 300 | H98: 330
A99: Retained Earnings | B99: 91.81 | C99: =(B99+C52) | D99: =(C99+D52) | E99: =(D99+E52) | F99: =(E99+F52) | G99: =(F99+G52) | H99: =(G99+H52)
A100: Total Shareholders' Equity | B100: =SUM(B98:B99) | C100: =SUM(C98:C99) | D100: =SUM(D98:D99) | E100: =SUM(E98:E99) | F100: =SUM(F98:F99) | G100: =SUM(G98:G99) | H100: =SUM(H98:H99)
A102: Total Liab. & Share. Equity | B102: =B82 | C102: =C82 | D102: =D82 | E102: =E82 | F102: =F82 | G102: =G82 | H102: =H82
A104: Debt / (Debt + Equity) | B104: =((B91+B94)/(B91+B94+B100)) | C104: =((C91+C94)/(C91+C94+C100)) | D104: =((D91+D94)/(D91+D94+D100)) | E104: =((E91+E94)/(E91+E94+E100)) | F104: =((F91+F94)/(F91+F94+F100)) | G104: =((G91+G94)/(G91+G94+G100)) | H104: =((H91+H94)/(H91+H94+H100))
A105: Market Price / Share | B105: 6.21 | C105: 6.57 | D105: 6.68 | E105: 6.71 | F105: =(F48*F10) | G105: =(G48*G10) | H105: =(H48*H10)
A106: External Funds Needed | B106: - | C106: =(C82-B82)-(C90-B90)-(C99-B99) | D106: =(D82-C82)-(D90-C90)-(D99-C99) | E106: =(E82-D82)-(E90-D90)-(E99-D99) | F106: =(F82-E82)-(F90-E90)-(F99-E99) | G106: =(G82-F82)-(G90-F90)-(G99-F99) | H106: =(H82-G82)-(H90-G90)-(H99-G99)
A115: Cash Flow Statement (Mil.$)
A116: Cash Flow From Operating Activities
A117: Net Income
A118: + Depreciation
A119: - Inc in Accts Receivable
A120: - Inc in Inventories
A121: + Inc in Accounts Payable
A122: Cash Flow From Operat Act
A124: Cash Flow From Investing Activities
A125: - Invest in Plant and Equip
A126: Cash Flow From Invest Act
A128: Cash Flow From Financing Activities
... A137: Cash and Equiv, End of Yr

Sheet Comparative
A1: ='Cover Page'!I2
A2: ='Cover Page'!I3 | B2: 2021 | C2: 2022 | D2: 2023 | E2: 2024 | F2: 2025 | G2: 2026 | H2: 2027
B3: Actual | C3: Actual | D3: Actual | E3: Actual | F3: Forecast | G3: Forecast | H3: Forecast
A5: Income Statement
A6: Sales
A7: Cost of Goods Sold
A8: Gross Margin
A10: Selling, Gen & Adm Expenses
A11: EBITDA
A13: Depreciation
A14: EBIT
A16: Interest Expense
A17: Taxes
A18: Net Income
A19: Shares Outstanding (Millions)
... A54: Total Liabilities and Equity

Sheet CommonSize
A1: ='Cover Page'!I2
A2: ='Cover Page'!I3 | B2: 2021 | C2: 2022 | D2: 2023 | E2: 2024 | F2: 2025 | G2: 2026 | H2: 2027
B3: Actual | C3: Actual | D3: Actual | E3: Actual | F3: Forecast | G3: Forecast | H3: Forecast
A5: Income Statement (%age of Sales)
A6: Sales
A7: Cost of Goods Sold
A8: Gross Margin
A10: Selling, Gen & Adm Expenses
A11: EBITDA
A13: Depreciation
A14: EBIT
A16: Interest Expense
A17: Taxes
A18: Net Income
A19: Shares Outstanding (Millions)
... A54: Total Liabilities and Equity

Sheet Ratios
A1: ='Cover Page'!I2
A2: ='Cover Page'!I3 | B2: 2021 | C2: 2022 | D2: 2023 | E2: 2024 | F2: 2025 | G2: 2026 | H2: 2027
B3: Actual | C3: Actual | D3: Actual | E3: Actual | F3: Forecast | G3: Forecast | H3: Forecast | J3: Formula Sheet
A4: Working Capital | J4: = Current Assets - Current Lib
A5: Current Ratio | J5: = Current Assets / Current Lib
A6: Collection Period | J6: = Average Acct. Rec / (Sales/365)
A7: Days to Sell Inventory | J7: = Average Inventory / (CGS/365)
A8: Total Debt to Equity | J8: = Total Lib / ShareHolder Eq
A9: Longterm Debt to Equity | J9: = Longterm Lib / ShareHolder Eq
A10: Times Interest Earned | J10: = EBIT / Int exp.
A11: Return on Assets | J11: = Net Income + Int. Exp (1-tax rate) / Avg. Total Assets
A12: Return on Equity | J12: = Net Income / Avg. Shareholder equity
A13: Gross Profit Margin | J13: = Sales - CGS / Sales
A14: Operating Profit Margin | J14: = Operating Income / Sales
A15: Net Profit Margin | J15: = Net Income / Sales
... A25: Dividend Payout rate | J25: = Cash Dividend per share / EPS

Sheet Valuation
A1: ='Cover Page'!I2
A2: ='Cover Page'!I3 | B2: 2021 | C2: 2022 | D2: 2023 | E2: 2024 | F2: 2025 | G2: 2026 | H2: 2027
B3: Actual | C3: Actual | D3: Actual | E3: Actual | F3: Forecast | G3: Forecast | H3: Forecast | I3: Terminal Value
A4: Assumption Multipliers
A5: EBITDA GROWTH RATE | E5: =(1+(Financials!E11))
A6: EBIT GROWTH RATE | E6: =(1+(Financials!E12))
A7: NWC Avg | E7: =-(1-(Financials!E13))
A8: Dep/Amo Avg Growth | E8: =(1+(Financials!E14))
A9: Capex Avg | E9: =(1+(Financials!E15))
A10: WACC | E10: =(1+(Financials!E16))
A11: Tax growth rate | E11: =(1+(Financials!E6))
A15: UFCF Using EBIT
A16: EBIT
A17: Less: Unlevered Taxes
A18: Net Operating Profit After Taxes (NOPAT)
A19: Add: Depreciation
A20: Less: Capex Investment
A21: Less: Change in working capital
A22: Unlevered Free Cash Flow (UFCF) using EBIT
A24: UFCF Using Net Income
A25: Net Income
A26: Depreciation
A27: After-tax Interest Expense (Int Exp * (1-Tax))
... A65: Weighted Average Target Price (Blended Method)
A66: Valuation Methodology | B66: Fair Value (SAR) | C66: Weightage | D66: Weighted value per share (SAR)
A67: DCF | B67: =B62 | C67: 0.5 | D67: =(B67*C67)
A68: Relative Valuation (EV/EBITDA) | C68: 0.3 | D68: =(B68*C68)
A69: Relative Valuation (P/E) | B69: =Ratios!E22 | C69: 0.2 | D69: =(B69*C69)
A70: Intrinsic Value (SAR) | C70: =SUM(C67:C69) | D70: =SUM(D67:D69)

Sheet ESG
A1: ='Cover Page'!I2
A2: ='Cover Page'!I3 | B2: 2021 | C2: 2022 | D2: 2023 | E2: 2024 | F2: 2025 | G2: 2026 | H2: 2027
B3: Actual | C3: Actual | D3: Actual | E3: Actual | F3: Forecast | G3: Forecast | H3: Forecast
A4: Environment
A5: Carbon Emission Initiatives
A6: Renewable energy sources
A11: Social
A12: Anti-bribery and anti corruption policy
A13: Health and safety policy
A14: Human rights policy
A15: Violations of Multinational Enterprise guidelines
A18: Governance
A19: Number of Male Members
A20: Number of Female Members
A21: Total Number of Board of Directors
A22: Percent of independent directors

Sheet Assumption G %
B1: Formula | C1: BITDA=[Net Income]+[Interest]+[TaxExpense]+[Depreciation/Amortization]
C2: (Current period Ebitda- Prior period Ebitda)/Prior period Ebitda
C3: EBIT = Net Income + Interest + Taxes
C4: Capital Expenditure (Capex) = Ending PP&E – Beginning PP&E + Depreciation
C5: Tax Growth Rate≈EBITDA Growth Rate
C6: Capital Expenditure (Capex) = Ending PP&E – Beginning PP&E + Depreciation
C8: 2022 | D8: 2023 | E8: 2024
B9: NET INCOME | C9: 124732624 | D9: 275066458 | E9: 280245234
B10: Interest | C10: 85012579 | D10: 89176512 | E10: 92974256
B11: TaxExpense | C11: 25330545 | D11: 17764317 | E11: 19082938
B12: EBIT | C12: =(C9+C10+C11) | D12: =(D9+D10+D11) | E12: =(E9+E10+E11)
B13: EBIT Growth | D13: =(D12-C12)/C12 | E13: =(E12-D12)/D12
B14: EBIT Avg G | E14: =(D13+E13)/2
B15: Dep/Amo | C15: =C10+C11 | D15: =D10+D11 | E15: =E10+E11
B16: EBITDA | C16: =C9+C10+C11+C15 | D16: =D9+D10+D11+D15 | E16: =E9+E10+E11+E15
B17: EBITDA Growth | D17: =(D16-C16)/C16 | E17: =(E16-D16)/D16
B18: EBITDA Avg G | E18: =(D17+E17)/2
B19: Tax growth rate | E19: =E18 | F19: Note*: Tax Growth Rate≈EBITDA Growth Rate
B21: current assests | C21: 1868043822 | D21: 2056499838 | E21: 1959730656
B22: current liability | C22: 1332923972 | D22: 1518606527 | E22: 1599205280
B23: NWC | C23: =C21-C22 | D23: =D21-D22 | E23: =E21-E22
B24: Change in NWC | E24: =E23-D23
B25: NWC Growth | D25: =(D23-C23)/C23 | E25: =(E23-D23)/D23
B26: NWC Avg Growth | E26: =(D25+E25)/2
C29: 2022 | D29: 2023 | E29: 2024
B30: DEP OF EQUIP | C30: 161551288 | D30: 162239379 | E30: 160500831
B31: DEP OF USE OF ASSEST | C31: 276211946 | D31: 285090168 | E31: 299074701
B32: TOTAL DEP/AMO | C32: =C30+C31 | D32: =D30+D31 | E32: =E30+E31
B33: Dep/Amo Growth | D33: =(D32-C32)/C32 | E33: =(E32-D32)/D32
B34: Dep/Amo Avg Growth | E34: =(D33+E33)/2
C36: 2022 | D36: 2022 | E36: 2022
B37: PPE | C37: 714432584 | D37: 773381888 | E37: 828614382
B38: Depreciation | C38: =C32 | D38: =D32 | E38: =E32
B39: Capex | D39: =(D37-C37)+D38 | E39: =(E37-D37)+E38
B40: Capex Avg | E40: =(E39-D39)/D39
B42: WACC | E42: 0.1 | F42: https://www.aljaziracapital.com.sa/media/3okaylhu/bindawood-investment-update-en.pdf
B45: EBITDA Multiple | E45: 10x | F45: https://www.aljaziracapital.com.sa/media/3okaylhu/bindawood-investment-update-en.pdf

Sheet Video_Links
A1: Supportive examples
A2: DCF MODELING STEP BY STEP | C2: https://www.youtube.com/watch?v=Gm0Xn_MidZ8&t=585s | I2: Very important step by step
A3: EBITDA | C3: https://www.youtube.com/watch?v=9oHbN90h_HU
A4: Upside potential | C4: https://www.investing.com/equities/bindawood-holding-co
A5: Price target | C5: https://www.tradingview.com/symbols/TADAWUL-4161/forecast/
A6: Analyst recommendation | C6: https://www.argaam.com/en/tadawul/tasi/bindawood
A7: WACC REPORT | C7: https://www.aljaziracapital.com.sa/media/3okaylhu/bindawood-investment-update-en.pdf
A9: Rating termonology
