Workbook

Sheet Income Statement
A1: البيان | B1: Statement | C1: القيمة / Amount | D1: % من المبيعات / % of Sales
C2: ='Data Input'!C3 -> Value
A3: المبيعات | B3: Sales Revenue | C3: ='Data Input'!C4 -> 0 | D3: =C3/$C$3 -> #DIV/0!
A4: تكلفة البضاعة المباعة | B4: Cost of Goods Sold (COGS) | C4: ='Data Input'!C5 -> 0 | D4: =C4/$C$3 -> #DIV/0!
F5: الباحث/ أحمد محمد مهلهل
A6: الربح الإجمالي | B6: Gross Profit | C6: =C3-C4 -> 0 | D6: =C6/$C$3 -> #DIV/0!
A9: المصروفات التشغيلية: | B9: Operating Expenses:
A10: مصروفات البيع والتسويق | B10: Selling & Marketing Expenses | C10: ='Data Input'!C6 -> 0 | D10: =C10/$C$3 -> #DIV/0!
A11: مصروفات إدارية | B11: Administrative Expenses | C11: ='Data Input'!C7 -> 0 | D11: =C11/$C$3 -> #DIV/0!
A12: مصروفات أخرى تشغيلية | B12: Other Operating Expenses | C12: ='Data Input'!C8 -> 0 | D12: =C12/$C$3 -> #DIV/0!
A13: إجمالي المصروفات التشغيلية | B13: Total Operating Expenses | C13: =SUM(C10:C12) -> 0 | D13: =C13/$C$3 -> #DIV/0!
A15: الربح التشغيلي (EBIT) | B15: Operating Income (EBIT) | C15: =C6-C13 -> 0 | D15: =C15/$C$3 -> #DIV/0!
A18: البنود غير التشغيلية: | B18: Non-Operating Items:
A19: إيرادات أخرى | B19: Other Income | C19: ='Data Input'!C9 -> 0 | D19: =C19/$C$3 -> #DIV/0!
A20: مصروفات أخرى | B20: Other Expenses | C20: ='Data Input'!C10 -> 0 | D20: =C20/$C$3 -> #DIV/0!
A21: الفائدة | B21: Interest Expense | C21: ='Data Input'!C11 -> 0 | D21: =C21/$C$3 -> #DIV/0!
A23: الربح قبل الضريبة | B23: Earnings Before Tax (EBT) | C23: =C15+C19-C20-C21 -> 0
A24: الضريبة | B24: Income Tax | C24: ='Data Input'!C12 -> 0 | D24: =C24/$C$3 -> #DIV/0!
A27: صافي الدخل | B27: NET INCOME | C27: =C23-C24 -> 0 | D27: =C27/$C$3 -> #DIV/0!

Sheet Financial Ratios
A1: مؤشر التحليل | B1: Financial Ratio | C1: الصيغة | D1: النتيجة | E1: التقييم
A3: نسب الربحية: | B3: PROFITABILITY RATIOS:
A4: هامش صافي الربح % | B4: Net Profit Margin % | C4: (Net Income / Sales) × 100 | D4: ='Income Statement'!C27/'Income Statement'!C3*100 -> #DIV/0!
A5: العائد على الأصول ROA % | B5: Return on Assets (ROA) % | C5: (Net Income / Total Assets) × 100 | D5: ='Income Statement'!C27/'Data Input'!C17*100 -> #DIV/0!
A6: العائد على حقوق المساهمين ROE % | B6: Return on Equity (ROE) % | C6: (Net Income / Equity) × 100 | D6: ='Income Statement'!C27/'Data Input'!C22*100 -> #DIV/0!
A8: نسب السيولة: | B8: LIQUIDITY RATIOS:
A9: النسبة الحالية | B9: Current Ratio | C9: Current Assets / Current Liabilities | D9: ='Data Input'!C15/'Data Input'!C19*100 -> #DIV/0!
A10: النسبة السريعة | B10: Quick Ratio | C10: (Current Assets - Inventory) / Current Liabilities | D10: =('Data Input'!C15-'Data Input'!C25)/'Data Input'!C19*100 -> #DIV/0!
A11: نسبة النقدية | B11: Cash Ratio | C11: Cash / Current Liabilities | D11: ='Data Input'!C30/'Data Input'!C19*100 -> #DIV/0!
A13: نسب الكفاءة: | B13: EFFICIENCY RATIOS:
A14: معدل دوران الأصول | B14: Asset Turnover Ratio | C14: Sales / Total Assets | D14: ='Data Input'!C4/'Data Input'!C17*100 -> #DIV/0!
A15: معدل دوران المخزون | B15: Inventory Turnover | C15: COGS / Average Inventory | D15: ='Data Input'!C5/'Data Input'!C25*100 -> #DIV/0!
A16: دورة تحويل النقدية | B16: Cash Conversion Cycle | C16: Days Inventory + Days Receivable - Days Payable
A18: نسب الالتزامات والملكية: | B18: LEVERAGE/SOLVENCY RATIOS:
A19: نسبة الدين إلى حقوق الملكية | B19: Debt to Equity Ratio | C19: Total Liabilities / Total Equity | D19: ='Data Input'!C21/'Data Input'!C22*100 -> #DIV/0!
A20: نسبة الدين إلى الأصول | B20: Debt to Assets Ratio | C20: Total Liabilities / Total Assets | D20: ='Data Input'!C21/'Data Input'!C17*100 -> #DIV/0!
A21: مرات تغطية الفائدة | B21: Interest Coverage Ratio | C21: EBIT / Interest Expense | D21: ='Income Statement'!C23/Table1[[#This Row],[القيمة / Amount]] -> #DIV/0!
A23: نسب السوق: | B23: MARKET/GROWTH RATIOS:
A24: نسبة السعر إلى الربح | B24: Price to Earnings (P/E) | C24: Stock Price / Earnings Per Share | D24: ='Data Input'!C28/('Income Statement'!C27/'Data Input'!C29)*100 -> #DIV/0!

Sheet Comparative Analysis
A1: البيان | B1: Item | C1: السنة الحالية | D1: Current Year | E1: السنة السابقة | F1: Previous Year | G1: التغير المطلق | H1: Absolute Change | I1: التغير النسبي % | J1: % Change
A3: المبيعات | B3: Sales Revenue | C3: ------- | E3: ------- | G3: ------- | H3: =D3-F3 -> 0 | I3: ------- | J3: =H3/F3 -> #DIV/0!
A4: تكلفة البضاعة المباعة | B4: COGS | C4: ------- | E4: ------- | G4: ------- | H4: =D4-F4 -> 0 | I4: ------- | J4: =H4/F4 -> #DIV/0!
A5: الربح الإجمالي | B5: Gross Profit | C5: ------- | E5: ------- | G5: ------- | H5: =D5-F5 -> 0 | I5: ------- | J5: =H5/F5 -> #DIV/0!
A6: المصروفات التشغيلية | B6: Operating Expenses | C6: ------- | E6: ------- | G6: ------- | H6: =D6-F6 -> 0 | I6: ------- | J6: =H6/F6 -> #DIV/0!
A7: الربح التشغيلي | B7: Operating Income | C7: ------- | E7: ------- | G7: ------- | H7: =D7-F7 -> 0 | I7: ------- | J7: =H7/F7 -> #DIV/0!
A8: صافي الدخل | B8: Net Income | C8: ------- | E8: ------- | G8: ------- | H8: =D8-F8 -> 0 | I8: ------- | J8: =H8/F8 -> #DIV/0!
C9: ------- | E9: ------- | G9: ------- | H9: =D9-F9 -> 0 | I9: ------- | J9: =H9/F9 -> #DIV/0!
A10: نسبة هامش الربح الإجمالي % | B10: Gross Margin % | C10: ------- | E10: ------- | G10: ------- | H10: =D10-F10 -> 0 | I10: ------- | J10: =H10/F10 -> #DIV/0!
A11: نسبة هامش الربح التشغيلي % | B11: Operating Margin % | C11: ------- | E11: ------- | G11: ------- | H11: =D11-F11 -> 0 | I11: ------- | J11: =H11/F11 -> #DIV/0!
A12: نسبة هامش صافي الربح % | B12: Net Profit Margin % | C12: ------- | E12: ------- | G12: ------- | H12: =D12-F12 -> 0 | I12: ------- | J12: =H12/F12 -> #DIV/0!

Sheet DuPont Analysis
A1: تحليل DuPont - ROE Decomposition | B1: Column1 | C1: الصيغة | D1: القيمة | E1: %
A3: العائد على حقوق الملاك (ROE) | B3: Return on Equity (ROE)
A4: هامش صافي الربح % | B4: Net Profit Margin % | C4: Net Income / Sales | D4: ='Income Statement'!C27/'Income Statement'!C3*100 -> #DIV/0! | E4: %
A5: × معدل دوران الأصول | B5: × Asset Turnover | C5: Sales / Total Assets | D5: ='Income Statement'!C3/'Data Input'!C17*100 -> #DIV/0! | E5: %
A6: × المضاعف المالي | B6: × Financial Multiplier | C6: Total Assets / Total Equity | D6: ='Data Input'!C17/'Data Input'!C22*100 -> #DIV/0! | E6: %
A8: التفسير: | B8: INTERPRETATION:
B9: Profitability: How much profit from each sale
B10: Efficiency: How efficiently assets are used
B11: Leverage: How much debt is used relative to equity

Sheet Data Input
A1: إدخال البيانات الأساسية - Data Input
A3: بيانات قائمة الدخل | B3: Income Statement Data | C3: Value
A4: المبيعات | B4: Sales Revenue
A5: تكلفة البضاعة المباعة | B5: COGS
A6: مصروفات البيع والتسويق | B6: Selling & Marketing
A7: مصروفات إدارية | B7: Administrative Expenses
A8: مصروفات أخرى تشغيلية | B8: Other Operating
A9: إيرادات أخرى | B9: Other Income | E9: الباحث/ أحمد محمد مهلهل
A10: مصروفات أخرى | B10: Other Expenses
A11: مصروفات الفائدة | B11: Interest Expense
A12: الضريبة | B12: Income Tax
A14: بيانات الميزانية العمومية | B14: Balance Sheet Data | C14: Value
A15: إجمالي الأصول الجارية | B15: Current Assets
A16: الأصول غير الجارية | B16: Non-Current Assets
A17: إجمالي الأصول | B17: Total Assets
A19: الالتزامات الجارية | B19: Current Liabilities
A20: الالتزامات طويلة الأجل | B20: Long-term Liabilities
A21: إجمالي الالتزامات | B21: Total Liabilities
A22: حقوق المساهمين | B22: Total Equity
A24: معلومات إضافية | B24: Additional Information | C24: Value
A25: المخزون | B25: Inventory
A26: الذمم المدينة | B26: Accounts Receivable
A27: الذمم الدائنة | B27: Accounts Payable
A28: سعر السهم | B28: Stock Price
A29: عدد الأسهم | B29: Number of Shares
A30: النقدية | B30: Cash
